{
  "config": {
    "name": "A0_plain_mmoe_id_only",
    "use_personalized_mmoe": false,
    "use_attribute_expert_mask": false,
    "use_personalized_gate": false,
    "use_task_bias": false,
    "use_target_attention": false,
    "use_auxiliary_loss": false,
    "use_item_side_features": false,
    "use_profile_features": false
  },
  "history": [
    {
      "epoch": 1,
      "train_loss": 1.3638070710003376,
      "val_loss": 0.6767793968319893,
      "click_logloss": 0.5961032785556767,
      "click_auc": 0.6613704345138023,
      "follow_logloss": 0.008256733413044658,
      "follow_auc": 0.5907764156450671,
      "like_logloss": 0.05652140224906263,
      "like_auc": 0.8685180513510483,
      "share_logloss": 0.016633218767394015,
      "share_auc": 0.650767818394258,
      "mean_auc": 0.6928581799760438
    }
  ]
}